{
  "timestamp": "20260216_143051",
  "status": "started",
  "data_rows": 5000,
  "data_source": "synthetic",
  "journal_trades": 0,
  "n_features": 22,
  "n_samples": 4941,
  "label_distribution": {
    "positive": 2089,
    "negative": 2852
  },
  "cv_competition": [
    {
      "algorithm": "lightgbm",
      "avg_auc": 0.502,
      "std_auc": 0.0266,
      "n_folds": 5,
      "folds": [
        {
          "fold": 1,
          "auc": 0.5492,
          "accuracy": 0.5808
        },
        {
          "fold": 2,
          "auc": 0.5119,
          "accuracy": 0.6869
        },
        {
          "fold": 3,
          "auc": 0.4749,
          "accuracy": 0.5354
        },
        {
          "fold": 4,
          "auc": 0.4908,
          "accuracy": 0.4823
        },
        {
          "fold": 5,
          "auc": 0.4834,
          "accuracy": 0.4924
        }
      ]
    }
  ],
  "best_algorithm": "lightgbm",
  "final_model": {
    "algorithm": "lightgbm",
    "auc": 0.5287,
    "accuracy": 0.496
  },
  "feature_importance": [
    {
      "feature": "volatility_20d",
      "importance": 359.46
    },
    {
      "feature": "volatility_5d",
      "importance": 351.98
    },
    {
      "feature": "ma60_ratio",
      "importance": 255.45
    },
    {
      "feature": "upper_shadow_ratio",
      "importance": 200.38
    },
    {
      "feature": "ret_1d",
      "importance": 191.48
    },
    {
      "feature": "ret_10d",
      "importance": 169.68
    },
    {
      "feature": "macd_histogram",
      "importance": 168.82
    },
    {
      "feature": "ret_5d",
      "importance": 150.45
    },
    {
      "feature": "ma5_ma20_cross",
      "importance": 149.0
    },
    {
      "feature": "lower_shadow_ratio",
      "importance": 128.1
    },
    {
      "feature": "ret_20d",
      "importance": 125.07
    },
    {
      "feature": "volume_ratio_5_20",
      "importance": 122.57
    },
    {
      "feature": "gap",
      "importance": 108.69
    },
    {
      "feature": "ma5_ratio",
      "importance": 107.23
    },
    {
      "feature": "macd_normalized",
      "importance": 101.31
    },
    {
      "feature": "price_position",
      "importance": 90.99
    },
    {
      "feature": "volume_change",
      "importance": 90.41
    },
    {
      "feature": "ma20_ratio",
      "importance": 68.45
    },
    {
      "feature": "rsi_14",
      "importance": 51.84
    },
    {
      "feature": "bollinger_pctb",
      "importance": 51.71
    },
    {
      "feature": "ma10_ratio",
      "importance": 50.83
    },
    {
      "feature": "intraday_range",
      "importance": 25.63
    }
  ],
  "model_path": "ml_models\\factor_model_20260216_143051.model"
}